tcpconnected.py
tcpconnected-0.1.0.dist-info/DESCRIPTION.rst
tcpconnected-0.1.0.dist-info/METADATA
tcpconnected-0.1.0.dist-info/RECORD
tcpconnected-0.1.0.dist-info/WHEEL
tcpconnected-0.1.0.dist-info/entry_points.txt
tcpconnected-0.1.0.dist-info/metadata.json
tcpconnected-0.1.0.dist-info/top_level.txt
