Metadata-Version: 2.0
Name: tcpconnected
Version: 0.1.0
Summary: A library for managing TCP Connected lighting devices
Home-page: https://github.com/azend/python-tcpconnected
Author: azend
Author-email: pypa+verdi@azend.org
License: MIT
Keywords: sample setuptools development
Platform: UNKNOWN
Classifier: Development Status :: 3 - Alpha
Classifier: Intended Audience :: Developers
Classifier: Topic :: Software Development :: Build Tools
Classifier: License :: OSI Approved :: MIT License
Classifier: Programming Language :: Python :: 2
Classifier: Programming Language :: Python :: 2.7
Classifier: Programming Language :: Python :: 3
Classifier: Programming Language :: Python :: 3.3
Classifier: Programming Language :: Python :: 3.4
Classifier: Programming Language :: Python :: 3.5
Requires-Dist: requests
Requires-Dist: untangle
Provides-Extra: dev
Provides-Extra: test
